<?xml version='1.0' encoding='UTF-8'?>
<song xmlns="http://openlyrics.info/namespace/2009/song" version="0.8" createdIn="OpenLP 2.0.5" modifiedIn="OpenLP 2.0.5" modifiedDate="2025-11-11T13:41:54+07:00">
 <properties>
  <titles><title>192 ขอพระเจ้าสดับคำร้องวิงวอนของข้า</title></titles>
  <authors><author> </author></authors>
 </properties>
 <lyrics>
  <verse name="v1"><lines>ขอพระเจ้าสดับ คำร้องวิงวอน ของข้า<br/>ยามข้าร้องทูลพระองค์ ด้วยใจที่<br/>ต้องการพึ่งพา</lines></verse>
  <verse name="c1"><lines>[ร้องรับ]<br/>และยามเมื่อใจของข้า ระอา<br/>ขอพระทรงเมตตา ให้ข้าใกล้<br/>พระศิลาที่สูงกว่า ข้าพระองค์</lines></verse>
  <verse name="v2"><lines>เพราะพระเจ้าทรงเป็นที่ลี้ภัย<br/>และพระศิลา ป้อมปราการมั่นคง<br/>โอบล้อมพิทักษ์รักษา</lines></verse>
  <verse name="c2"><lines>[ร้องรับ]<br/>และยามเมื่อใจของข้า ระอา<br/>ขอพระทรงเมตตา ให้ข้าใกล้<br/>พระศิลาที่สูงกว่า ข้าพระองค์</lines></verse>
 </lyrics>
</song>

