<?xml version='1.0' encoding='UTF-8'?>
<song xmlns="http://openlyrics.info/namespace/2009/song" version="0.8" createdIn="OpenLP 2.0.5" modifiedIn="OpenLP 2.0.5" modifiedDate="2025-11-11T13:41:54+07:00">
 <properties>
  <titles><title>228 นิมิต</title></titles>
  <authors><author> </author></authors>
 </properties>
 <lyrics>
  <verse name="v1"><lines>ข้าขอวิงวอนพระเยซู<br/>โปรดนำชีวิตข้างหน้าต่อไป<br/>จะเป็นอย่างไรไม่รู้ แต่วันนี้ตัดสินใจ<br/>มอบตัวและใจดวงนี้ รับใช้พระองค์</lines></verse>
  <verse name="v2"><lines>โปรดให้ข้าเห็นนิมิตในประเทศไทย<br/>โปรดส่งข้าไปเล่าความเป็นจริง<br/>ให้คนไทยได้รู้<br/>ข้าปรารถนารับใช้พระองค์ผู้มีชีวิตอยู่<br/>ข้ารู้พระองค์จะนำทางข้าไป<br/>จนสิ้นลมหายใจ</lines></verse>
 </lyrics>
</song>

