<?xml version='1.0' encoding='UTF-8'?>
<song xmlns="http://openlyrics.info/namespace/2009/song" version="0.8" createdIn="OpenLP 2.0.5" modifiedIn="OpenLP 2.0.5" modifiedDate="2025-11-11T13:41:54+07:00">
 <properties>
  <titles><title>239 สรรเสริญและโมทนา</title></titles>
  <authors><author> </author></authors>
 </properties>
 <lyrics>
  <verse name="v1"><lines>สรรเสริญและโมทนา พระองค์ผู้ทรงเมตตา<br/>ทรงไถ่ข้า และชนทุกชาติพันธุ์<br/>สรรเสริญและสดุดี พระองค์ผู้ทรงฤทธี<br/>ดวงใจนี้ ขอมอบแด่พระองค์</lines></verse>
 </lyrics>
</song>

