<?xml version='1.0' encoding='UTF-8'?>
<song xmlns="http://openlyrics.info/namespace/2009/song" version="0.8" createdIn="OpenLP 2.0.5" modifiedIn="OpenLP 2.0.5" modifiedDate="2026-01-12T11:54:09+07:00">
 <properties>
  <titles><title>45 ข้ารับการไถ่</title></titles>
  <authors><author> </author></authors>
 </properties>
 <lyrics>
  <verse name="v1"><lines>ข้ารับการไถ่ ๆ ด้วยพระโลหิต ๆ<br/>ข้ารับการไถ่ ๆ ข้ารู้แน่แก่ใจ ๆ<br/>ข้ารับการไถ่ด้วยพระโลหิต หลุดจากบาป<br/>เป็นที่ทราบแน่ใจ บาปของข้าถูกยกแล้ว<br/>สรรเสริญพระเจ้า</lines></verse>
 </lyrics>
</song>

