<?xml version='1.0' encoding='UTF-8'?>
<song xmlns="http://openlyrics.info/namespace/2009/song" version="0.8" createdIn="OpenLP 2.0.5" modifiedIn="OpenLP 2.0.5" modifiedDate="2025-11-11T13:41:54+07:00">
 <properties>
  <titles><title>495B แสงสว่างแห่งพระคริสต์</title></titles>
  <authors><author> </author></authors>
 </properties>
 <lyrics>
  <verse name="v1"><lines>สรรเสริญพระเจ้าแห่งดวงใจ<br/>เป็นนิมิตมาย ถวายแด่พระองค์<br/>พระคุณล้ำเลิศ ประเสริฐความรักมั่นคง<br/>อาทิตย์ดับลง คืนนี้มีแสงจันทร์</lines></verse>
  <verse name="v2"><lines>โอดวงดาวคืนนี้สวยเรียงลาย<br/>ส่องแสงอำภัยพระองค์ทรงประทาน<br/>เสริมสร้างประกายดวงใจอธิษฐาน<br/>ชีวิตวิญญาณพระองค์ทรงเมตตา</lines></verse>
  <verse name="v3"><lines>โอ พระเจ้าชักนำแสงสว่าง<br/>ส่องหนทาง ดลจิตชีวิตข้า<br/>อย่าหลับไหล ให้มารร้ายชักนำพา<br/>ตื่นเถิดหน้าแหงนดูฟ้า รับดวงตะวัน</lines></verse>
  <verse name="v4"><lines>สรรเสริญเหนือเกล้าองค์พระคริสต์<br/>ประทานชีวิตสถิตใจข้านิรันดร์<br/>องค์พระบิดา อยู่บนฟ้าสวรรค์<br/>ถ่อมใจของท่าน นมัสการพระองค์<br/>ฮาเลลูยา ฮาเลลูยา ฮาเลลูยา ฮาเลลูยา</lines></verse>
 </lyrics>
</song>

