<?xml version='1.0' encoding='UTF-8'?>
<song xmlns="http://openlyrics.info/namespace/2009/song" version="0.8" createdIn="OpenLP 2.0.5" modifiedIn="OpenLP 2.0.5" modifiedDate="2025-11-11T13:41:54+07:00">
 <properties>
  <titles><title>596 เราขอนมัสการ</title></titles>
  <authors><author> </author></authors>
 </properties>
 <lyrics>
  <verse name="v1"><lines>เราขอนมัสการพระองค์ ทรงเป็นพระเจ้า<br/>จอมราชา ประทับบนบัลลังก์โสภา<br/>ทรงนามว่าพระเยซู ทรงมีฤทธิ์อำนาจ<br/>เหนือพญามารครอบครองสวรรค์และ<br/>โลกา ไม่มีสิ่งใดเป็นไปไม่ได้<br/>สำหรับองค์ทรงนามเยซู</lines></verse>
  <verse name="c1"><lines>[ร้องรับ]<br/>เราจะยกย่องสรรเสริญ<br/>ชูมือนมัสการ พระนามผู้ทรงเป็นจอมราชา<br/>เปล่งเสียงถวายคำสดุดี<br/>แด่องค์พระภูมี ทรงนามเยซู</lines></verse>
 </lyrics>
</song>

